odoo/addons/agreement/README.rst
odoo/addons/agreement/__init__.py
odoo/addons/agreement/__manifest__.py
odoo/addons/agreement/demo/demo.xml
odoo/addons/agreement/i18n/agreement.pot
odoo/addons/agreement/i18n/ca.po
odoo/addons/agreement/i18n/es.po
odoo/addons/agreement/i18n/es_AR.po
odoo/addons/agreement/i18n/fr.po
odoo/addons/agreement/i18n/fr_FR.po
odoo/addons/agreement/i18n/hr.po
odoo/addons/agreement/i18n/it.po
odoo/addons/agreement/i18n/nl.po
odoo/addons/agreement/i18n/pt.po
odoo/addons/agreement/i18n/pt_BR.po
odoo/addons/agreement/i18n/pt_PT.po
odoo/addons/agreement/i18n/zh_CN.po
odoo/addons/agreement/models/__init__.py
odoo/addons/agreement/models/agreement.py
odoo/addons/agreement/models/agreement_type.py
odoo/addons/agreement/readme/CONTRIBUTORS.rst
odoo/addons/agreement/readme/DESCRIPTION.rst
odoo/addons/agreement/security/agreement_security.xml
odoo/addons/agreement/security/ir.model.access.csv
odoo/addons/agreement/static/description/icon.png
odoo/addons/agreement/static/description/index.html
odoo/addons/agreement/tests/__init__.py
odoo/addons/agreement/tests/test_agreement.py
odoo/addons/agreement/views/agreement.xml
odoo/addons/agreement/views/agreement_type.xml
odoo14_addon_agreement-14.0.1.1.1.dist-info/METADATA
odoo14_addon_agreement-14.0.1.1.1.dist-info/WHEEL
odoo14_addon_agreement-14.0.1.1.1.dist-info/top_level.txt
odoo14_addon_agreement-14.0.1.1.1.dist-info/RECORD
